flux_tool/__init__.py
flux_tool/beam_focusing_systematics.py
flux_tool/config.py
flux_tool/exporter.py
flux_tool/flux_systematics_analysis.py
flux_tool/hadron_production_systematics.py
flux_tool/helpers.py
flux_tool/main.py
flux_tool/normalize_and_rebin_data.py
flux_tool/preprocessor.py
flux_tool/principal_component_analysis.py
flux_tool/uncertainty.py
flux_tool/vis_scripts/__init__.py
flux_tool/vis_scripts/covariance.py
flux_tool/vis_scripts/flux_prediction.py
flux_tool/vis_scripts/fractional_uncertainties.py
flux_tool/vis_scripts/helper.py
flux_tool/vis_scripts/parent_spectra.py
flux_tool/vis_scripts/pca_plots.py
flux_tool/vis_scripts/plot_all.py
flux_tool/vis_scripts/ppfx_universes.py
flux_tool/vis_scripts/spectra_reader.py
flux_tool/vis_scripts/style.py
flux_tool-1.5.1.dist-info/METADATA
flux_tool-1.5.1.dist-info/WHEEL
flux_tool-1.5.1.dist-info/entry_points.txt
flux_tool-1.5.1.dist-info/licenses/LICENSE
flux_tool-1.5.1.dist-info/RECORD
