Metadata-Version: 2.4
Name: flux-tool
Version: 1.5.1
Summary: Package used to study the output histograms from PPFX
Author-email: Anthony Wood <apwood@uh.edu>
License-File: LICENSE
Requires-Python: >=3.13
Requires-Dist: hist>=2.8.0
Requires-Dist: jinja2>=3.1.6
Requires-Dist: matplotlib>=3.10.0
Requires-Dist: mplhep>=0.3.55
Requires-Dist: numpy>=2.2.2
Requires-Dist: pandas>=2.2.3
Requires-Dist: rich>=13.9.4
Requires-Dist: scipy>=1.15.1
Requires-Dist: seaborn>=0.13.2
Requires-Dist: uproot>=5.5.1
